.gitignore
.readthedocs.yaml
LICENSE
MANIFEST.in
README.md
setup.py
.github/workflows/main.yml
docs/Makefile
docs/make.bat
docs/requirements.txt
docs/source/caveats.rst
docs/source/conf.py
docs/source/example_plot.png
docs/source/example_post.png
docs/source/examples.rst
docs/source/faqs.rst
docs/source/gyrointerp.rst
docs/source/gyrointerp_logo.png
docs/source/index.rst
docs/source/installation.rst
drivers/README.md
drivers/calculate_representative_uncertainties.py
drivers/check_mist_teff_evolution.py
drivers/get_mist_teff_at_zams.py
drivers/get_polyorder_stats.py
drivers/make_prot_teff_cluster_comparison_frames.py
drivers/make_prot_teff_movie.py
drivers/plot_age_posteriors.py
drivers/plot_cdf_fast_slow_ratio.py
drivers/plot_crossvalidation_cdf_fast_slow_ratio.py
drivers/plot_data_vs_model_prot.py
drivers/plot_empirical_limits_of_gyrochronology.py
drivers/plot_extraptest_prot_vs_time.py
drivers/plot_n_vs_teff_vs_time.py
drivers/plot_prot_vs_teff.py
drivers/plot_prot_vs_teff_residual.py
drivers/plot_prot_vs_time_fixed_teff.py
drivers/plot_slow_sequence_residual.py
drivers/pop_hyperparameter_pkl_to_csv.py
drivers/read_mist_model.py
drivers/run_crossvalidation_emcee_fit_gyro_model.py
drivers/run_emcee_fit_gyro_model.py
drivers/run_m34_verification.py
drivers/run_m37_verification.py
drivers/run_prot_teff_grid.py
drivers/run_train_verification.py
drivers/write_rotation_period_table.py
drivers/deprecated/concatenate_fit_gyro_model_output.py
drivers/deprecated/evaluate_fit_gyro_bestfit_params.py
drivers/deprecated/fitting.py
drivers/deprecated/plot_example_age_posteriors.py
drivers/deprecated/plot_fit_gyro_model.py
drivers/deprecated/run_parallel_fit_gyro_model.py
gyrointerp/__init__.py
gyrointerp/age_scale.py
gyrointerp/extinctionpriors.py
gyrointerp/getters.py
gyrointerp/gyro_posterior.py
gyrointerp/helpers.py
gyrointerp/models.py
gyrointerp/paths.py
gyrointerp/plotting.py
gyrointerp/teff.py
gyrointerp.egg-info/PKG-INFO
gyrointerp.egg-info/SOURCES.txt
gyrointerp.egg-info/dependency_links.txt
gyrointerp.egg-info/not-zip-safe
gyrointerp.egg-info/requires.txt
gyrointerp.egg-info/top_level.txt
gyrointerp/data/interim/M34/Meibom_2011_X_GaiaDR2.csv
