Metadata-Version: 2.1
Name: gyrointerp
Version: 0.7
Summary: Gyrochronology via interpolation of open cluster rotation sequences.
Home-page: https://github.com/lgbouma/gyro-interp
Download-URL: https://github.com/lgbouma/gyro-interp/archive/refs/tags/v07.tar.gz
Author: Luke Bouma
Author-email: bouma.luke@gmail.com
License: MIT
Keywords: astronomy
Classifier: Development Status :: 3 - Alpha
Classifier: License :: OSI Approved :: MIT License
Classifier: Intended Audience :: Science/Research
Classifier: Topic :: Scientific/Engineering :: Astronomy
Classifier: Operating System :: OS Independent
Classifier: Programming Language :: Python :: 3
License-File: LICENSE
Requires-Dist: numpy>=1.4.0
Requires-Dist: scipy>=1.7.0
Requires-Dist: pandas>=1.2.4
Requires-Dist: astropy>=4.0.4
Requires-Dist: matplotlib
Provides-Extra: all
Requires-Dist: cdips; extra == "all"
